sonata/__init__.py
django_sonata-0.0.1.dev0.dist-info/LICENSE
django_sonata-0.0.1.dev0.dist-info/METADATA
django_sonata-0.0.1.dev0.dist-info/WHEEL
django_sonata-0.0.1.dev0.dist-info/top_level.txt
django_sonata-0.0.1.dev0.dist-info/RECORD
