Metadata-Version: 2.1
Name: django-sonata
Version: 0.0.1.dev0
Summary: A modern, responsive and customizable theme with many flavors (bootstrap, material design) for django admin.
Home-page: https://github.com/cizario/django-sonata/
Author: Nizar DELLELI
Author-email: nizar.delleli@gmail.com
License: BSD-3-Clause
Download-URL: https://github.com/cizario/django-sonata/
Project-URL: Issue Tracker, https://github.com/cizario/django-sonata/issues
Project-URL: Source Code, https://github.com/cizario/django-sonata/
Project-URL: Documentation, https://django-sonata.readthedocs.io/en/latest/
Keywords: django admin theme,sonata admin theme,bootstrap,materialdesign
Platform: any
Classifier: Development Status :: 1 - Planning
Classifier: Framework :: Django
Classifier: Intended Audience :: Developers
Classifier: License :: OSI Approved :: BSD License
Classifier: Operating System :: OS Independent
Classifier: Programming Language :: JavaScript
Classifier: Programming Language :: Python
Classifier: Programming Language :: Python :: 3
Classifier: Programming Language :: Python :: 3.6
Classifier: Programming Language :: Python :: 3.7
Classifier: Programming Language :: Python :: 3.8
Classifier: Programming Language :: Python :: 3.9
Classifier: Programming Language :: Python :: 3 :: Only
Requires-Python: >=3.6
License-File: LICENSE
Requires-Dist: Django
